Metadata-Version: 1.1
Name: azurlane
Version: 1.1.1
Summary: Unofficial Azur Lane API library made in Python
Home-page: https://github.com/AzurAPI/azurapi-py
Author: August, Spimy
Author-email: august@augu.dev
License: UNKNOWN
Keywords: azurlane,azur lane
Platform: UNKNOWN
Classifier: Programming Language :: Python :: 3.7
